deep_time_series/__init__.py
deep_time_series/chunk.py
deep_time_series/core.py
deep_time_series/dataset.py
deep_time_series/function.py
deep_time_series/layer.py
deep_time_series/model/__init__.py
deep_time_series/model/dilated_cnn.py
deep_time_series/model/mlp.py
deep_time_series/model/rnn.py
deep_time_series/model/single_shot_transformer.py
deep_time_series/plotting.py
deep_time_series/transform.py
deep_time_series/util.py
deep_time_series-0.1.2.dist-info/METADATA
deep_time_series-0.1.2.dist-info/WHEEL
deep_time_series-0.1.2.dist-info/RECORD
